EventProcces-1.2.dist-info/METADATA
EventProcces-1.2.dist-info/RECORD
EventProcces-1.2.dist-info/WHEEL
EventProcces-1.2.dist-info/top_level.txt
event/Event.py
event/EventClass.py
event/__init__.py
functions/DisplayFunctions.py
functions/Functions.py
functions/__init__.py
