Metadata-Version: 2.1
Name: EventProcces
Version: 1.2
Summary: Package to process events in Calendar
Home-page: UNKNOWN
Author: Artur
Author-email: artur@wp.com
License: UNKNOWN
Platform: UNKNOWN
